dictmerge.py
dictmerge-0.2.0.dist-info/DESCRIPTION.rst
dictmerge-0.2.0.dist-info/METADATA
dictmerge-0.2.0.dist-info/metadata.json
dictmerge-0.2.0.dist-info/RECORD
dictmerge-0.2.0.dist-info/top_level.txt
dictmerge-0.2.0.dist-info/WHEEL
