Metadata-Version: 2.0
Name: dictmerge
Version: 0.2.0
Summary: Merge dicts without mutating them.
Home-page: https://github.com/nvie/dictmerge
Author: Vincent Driessen
Author-email: me@nvie.com
License: BSD
Platform: any
Classifier: Development Status :: 5 - Production/Stable
Classifier: Intended Audience :: Developers
Classifier: Operating System :: OS Independent
Classifier: Programming Language :: Python
Classifier: Programming Language :: Python :: 2
Classifier: Programming Language :: Python :: 3
